Metadata-Version: 2.1
Name: justrandomlibrary
Version: 0.1.0
Summary: Super useful library
Author: Mikolaj Kalejta
Author-email: kalejtamikolaj@wp.pl
